routemap/__init__.py
routemap/__main__.py
routemap/__version__.py
routemap/routemap.py
routemap-2.0.0.dist-info/LICENSE
routemap-2.0.0.dist-info/METADATA
routemap-2.0.0.dist-info/WHEEL
routemap-2.0.0.dist-info/entry_points.txt
routemap-2.0.0.dist-info/top_level.txt
routemap-2.0.0.dist-info/RECORD
