Metadata-Version: 2.1
Name: routemap
Version: 2.0.0
Summary: Generate route maps from various sources.
Home-page: https://gitlab.com/vascowhite/routemap
Author: Paul White
Author-email: routemap@vascowhite.co.uk
License: MIT
Platform: UNKNOWN
Requires-Dist: pyproj
Requires-Dist: pyshp
Requires-Dist: pandas
Requires-Dist: six
Requires-Dist: Pillow
Requires-Dist: requests
Requires-Dist: vincenty
Requires-Dist: geographiclib
Requires-Dist: scipy
